cachekit-0.2.3.dist-info/METADATA
cachekit-0.2.3.dist-info/WHEEL
cachekit-0.2.3.dist-info/licenses/LICENSE
cachekit/__init__.py
cachekit/_rust_serializer.cpython-311-x86_64-linux-gnu.so
cachekit/backends/__init__.py
cachekit/backends/base.py
cachekit/backends/errors.py
cachekit/backends/file/__init__.py
cachekit/backends/file/backend.py
cachekit/backends/file/config.py
cachekit/backends/provider.py
cachekit/backends/redis/__init__.py
cachekit/backends/redis/backend.py
cachekit/backends/redis/client.py
cachekit/backends/redis/config.py
cachekit/backends/redis/error_handler.py
cachekit/backends/redis/provider.py
cachekit/cache_handler.py
cachekit/config/__init__.py
cachekit/config/decorator.py
cachekit/config/nested.py
cachekit/config/settings.py
cachekit/config/singleton.py
cachekit/config/validation.py
cachekit/decorators/__init__.py
cachekit/decorators/intent.py
cachekit/decorators/main.py
cachekit/decorators/orchestrator.py
cachekit/decorators/session.py
cachekit/decorators/stats_context.py
cachekit/decorators/tenant_context.py
cachekit/decorators/utils/__init__.py
cachekit/decorators/wrapper.py
cachekit/di.py
cachekit/hash_utils.py
cachekit/health.py
cachekit/hiredis_compat.py
cachekit/imports.py
cachekit/invalidation/__init__.py
cachekit/invalidation/channel.py
cachekit/invalidation/event.py
cachekit/invalidation/redis_channel.py
cachekit/key_generator.py
cachekit/l1_cache.py
cachekit/logging.py
cachekit/monitoring/__init__.py
cachekit/monitoring/correlation_tracking.py
cachekit/monitoring/pool_monitor.py
cachekit/monitoring/protocols.py
cachekit/py.typed
cachekit/reliability/__init__.py
cachekit/reliability/adaptive_timeout.py
cachekit/reliability/async_metrics.py
cachekit/reliability/circuit_breaker.py
cachekit/reliability/error_classification.py
cachekit/reliability/load_control.py
cachekit/reliability/metrics_collection.py
cachekit/reliability/profiles.py
cachekit/serializers/__init__.py
cachekit/serializers/arrow_serializer.py
cachekit/serializers/auto_serializer.py
cachekit/serializers/base.py
cachekit/serializers/encryption_wrapper.py
cachekit-0.2.3.dist-info/RECORD
