Metadata-Version: 2.4
Name: cachekit
Version: 0.2.3
Classifier: Development Status :: 3 - Alpha
Classifier: Intended Audience :: Developers
Classifier: License :: OSI Approved :: MIT License
Classifier: Operating System :: OS Independent
Classifier: Programming Language :: Python :: 3
Classifier: Programming Language :: Python :: 3.9
Classifier: Programming Language :: Python :: 3.10
Classifier: Programming Language :: Python :: 3.11
Classifier: Programming Language :: Python :: 3.12
Classifier: Programming Language :: Python :: 3.13
Classifier: Programming Language :: Python :: Implementation :: CPython
Classifier: Programming Language :: Rust
Classifier: Topic :: Software Development :: Libraries :: Python Modules
Classifier: Topic :: Database :: Database Engines/Servers
Classifier: Topic :: System :: Distributed Computing
Classifier: Topic :: System :: Monitoring
Classifier: Topic :: Security :: Cryptography
Classifier: Framework :: AsyncIO
Classifier: Typing :: Typed
Requires-Dist: redis[hiredis]>=4.0.0
Requires-Dist: pydantic>=2.0.0
Requires-Dist: pydantic-settings>=2.0.0
Requires-Dist: tenacity>=8.0.0
Requires-Dist: prometheus-client>=0.22.1
Requires-Dist: psutil>=7.0.0
Requires-Dist: blake3>=1.0.5
Requires-Dist: msgpack>=1.1.2
Requires-Dist: orjson>=3.9.0
Requires-Dist: xxhash>=3.5.0
Requires-Dist: numpy>=2.0.2 ; extra == 'data'
Requires-Dist: pandas>=1.3.0 ; extra == 'data'
Requires-Dist: pyarrow>=21.0.0 ; extra == 'data'
Provides-Extra: data
License-File: LICENSE
Summary: Production-ready Redis caching for Python with intelligent reliability features and Rust-powered performance
Keywords: redis,cache,caching,decorator,rust,performance,reliability,production,encryption,security,circuit-breaker,prometheus,messagepack,distributed-locking
Home-Page: https://github.com/cachekit-io/cachekit-py
Author-email: cachekit Contributors <noreply@cachekit.io>
Maintainer-email: cachekit Contributors <noreply@cachekit.io>
License: MIT
Requires-Python: >=3.9
Project-URL: Homepage, https://github.com/cachekit-io/cachekit-py
Project-URL: Documentation, https://github.com/cachekit-io/cachekit-py#readme
Project-URL: Repository, https://github.com/cachekit-io/cachekit-py.git
Project-URL: Issues, https://github.com/cachekit-io/cachekit-py/issues
Project-URL: Changelog, https://github.com/cachekit-io/cachekit-py/blob/main/CHANGELOG.md
